README.md
setup.py
pylsar/__init__.py
pylsar/pylsar.py
pylsar.egg-info/PKG-INFO
pylsar.egg-info/SOURCES.txt
pylsar.egg-info/dependency_links.txt
pylsar.egg-info/entry_points.txt
pylsar.egg-info/requires.txt
pylsar.egg-info/top_level.txt