Metadata-Version: 2.1
Name: pylsar
Version: 0.0.0
Summary: A scenarised REST API test tool
Home-page: https://framagit.org/zesk06/pylsar
Author: Nicolas Rouviere
Author-email: zesk06@gmail.com
License: BSD
Keywords: REST requests
Platform: UNKNOWN
Classifier: Development Status :: 3 - Alpha
Classifier: Topic :: Utilities
Classifier: Environment :: Console
Classifier: Intended Audience :: Developers
Classifier: License :: OSI Approved :: MIT License
Classifier: Programming Language :: Python
Classifier: Programming Language :: Python :: 3
Classifier: Programming Language :: Python :: 3.6
Classifier: Programming Language :: Python :: 3.7
Classifier: Topic :: Software Development
Classifier: License :: OSI Approved :: BSD License
Provides-Extra: dev
